pycontentdb
