Metadata-Version: 1.1
Name: pycontentdb
Version: 0.1.1
Summary: Retrieves Data from contentdb
Home-page: https://gitlab.com/Niwla23/pycontentdb
Author: Alwin Lohrie (Niwla23)
Author-email: alwin.l@gmx.de
License: MIT
Download-URL: https://gitlab.com/Niwla23/pycontentdb
Keywords: minetest,contentdb
Platform: UNKNOWN
Classifier: Development Status :: 5 - Production/Stable
Classifier: Intended Audience :: Developers
Classifier: Topic :: Software Development :: Build Tools
Classifier: License :: OSI Approved :: MIT License
Classifier: Programming Language :: Python :: 3
Classifier: Programming Language :: Python :: 3.5
Classifier: Programming Language :: Python :: 3.6
Classifier: Programming Language :: Python :: 3.7
Classifier: Programming Language :: Python :: 3.8
